[
    {
        "country": "COL",
        "make": "VW",
        "model": "Cross Fox",
        "type": "Cars",
        "segment": "A",
        "powertrain": "N/A",
        "sales": {
            "2000": 0,
            "2001": 0,
            "2002": 0,
            "2003": 0,
            "2004": 0,
            "2005": 0,
            "2006": 0,
            "2007": 0,
            "2008": 0,
            "2009": 0,
            "2010": 0,
            "2011": 0,
            "2012": 0,
            "2013": 729,
            "2014": 710,
            "2015": 606,
            "2016": 538,
            "2017": 616,
            "2018": 0,
            "2019": 0,
            "2020": 0,
            "2021": 1,
            "2022": 0,
            "2023": 0
        }
    },
    {
        "country": "COL",
        "make": "VW",
        "model": "Lupo/Fox",
        "type": "Cars",
        "segment": "A",
        "powertrain": "N/A",
        "sales": {
            "2000": 0,
            "2001": 0,
            "2002": 0,
            "2003": 0,
            "2004": 0,
            "2005": 0,
            "2006": 0,
            "2007": 0,
            "2008": 0,
            "2009": 0,
            "2010": 0,
            "2011": 378,
            "2012": 690,
            "2013": 0,
            "2014": 0,
            "2015": 0,
            "2016": 0,
            "2017": 0,
            "2018": 0,
            "2019": 0,
            "2020": 0,
            "2021": 0,
            "2022": 1,
            "2023": 0
        }
    },
    {
        "country": "COL",
        "make": "VW",
        "model": "Lupo/Fox",
        "type": "Cars",
        "segment": "A",
        "powertrain": null,
        "sales": {
            "2000": 0,
            "2001": 0,
            "2002": 0,
            "2003": 0,
            "2004": 0,
            "2005": 0,
            "2006": 0,
            "2007": 0,
            "2008": 0,
            "2009": 0,
            "2010": 0,
            "2011": 378,
            "2012": 690,
            "2013": 729,
            "2014": 710,
            "2015": 606,
            "2016": 538,
            "2017": 616,
            "2018": 0,
            "2019": 0,
            "2020": 0,
            "2021": 1,
            "2022": 1,
            "2023": 0
        }
    },
    {
        "country": "COL",
        "make": "VW",
        "model": "Gol",
        "type": "Cars",
        "segment": "B",
        "powertrain": "N/A",
        "sales": {
            "2000": 0,
            "2001": 0,
            "2002": 0,
            "2003": 0,
            "2004": 0,
            "2005": 0,
            "2006": 0,
            "2007": 0,
            "2008": 0,
            "2009": 0,
            "2010": 1669,
            "2011": 1424,
            "2012": 3115,
            "2013": 2622,
            "2014": 2588,
            "2015": 2056,
            "2016": 2820,
            "2017": 2773,
            "2018": 3080,
            "2019": 3891,
            "2020": 1449,
            "2021": 3441,
            "2022": 4953,
            "2023": 0
        }
    },
    {
        "country": "COL",
        "make": "VW",
        "model": "Polo",
        "type": "Cars",
        "segment": "B",
        "powertrain": "N/A",
        "sales": {
            "2000": 0,
            "2001": 0,
            "2002": 0,
            "2003": 0,
            "2004": 0,
            "2005": 0,
            "2006": 0,
            "2007": 0,
            "2008": 0,
            "2009": 0,
            "2010": 0,
            "2011": 0,
            "2012": 0,
            "2013": 0,
            "2014": 0,
            "2015": 0,
            "2016": 0,
            "2017": 0,
            "2018": 0,
            "2019": 0,
            "2020": 0,
            "2021": 794,
            "2022": 261,
            "2023": 0
        }
    },
    {
        "country": "COL",
        "make": "VW",
        "model": "Virtus",
        "type": "Cars",
        "segment": "B",
        "powertrain": "N/A",
        "sales": {
            "2000": 0,
            "2001": 0,
            "2002": 0,
            "2003": 0,
            "2004": 0,
            "2005": 0,
            "2006": 0,
            "2007": 0,
            "2008": 0,
            "2009": 0,
            "2010": 0,
            "2011": 0,
            "2012": 0,
            "2013": 0,
            "2014": 0,
            "2015": 0,
            "2016": 0,
            "2017": 0,
            "2018": 0,
            "2019": 0,
            "2020": 0,
            "2021": 1140,
            "2022": 443,
            "2023": 0
        }
    },
    {
        "country": "COL",
        "make": "VW",
        "model": "Voyage",
        "type": "Cars",
        "segment": "B",
        "powertrain": "N/A",
        "sales": {
            "2000": 0,
            "2001": 0,
            "2002": 0,
            "2003": 0,
            "2004": 0,
            "2005": 0,
            "2006": 0,
            "2007": 0,
            "2008": 0,
            "2009": 0,
            "2010": 0,
            "2011": 0,
            "2012": 0,
            "2013": 0,
            "2014": 0,
            "2015": 0,
            "2016": 0,
            "2017": 0,
            "2018": 2356,
            "2019": 2226,
            "2020": 1748,
            "2021": 2253,
            "2022": 2716,
            "2023": 0
        }
    },
    {
        "country": "COL",
        "make": "VW",
        "model": "Voyage",
        "type": "Cars",
        "segment": "B",
        "powertrain": null,
        "sales": {
            "2000": 0,
            "2001": 0,
            "2002": 0,
            "2003": 0,
            "2004": 0,
            "2005": 0,
            "2006": 0,
            "2007": 0,
            "2008": 0,
            "2009": 0,
            "2010": 1669,
            "2011": 1424,
            "2012": 3115,
            "2013": 2622,
            "2014": 2588,
            "2015": 2056,
            "2016": 2820,
            "2017": 2773,
            "2018": 5436,
            "2019": 6117,
            "2020": 3197,
            "2021": 7628,
            "2022": 8373,
            "2023": 0
        }
    },
    {
        "country": "COL",
        "make": "VW",
        "model": "Beetle",
        "type": "Cars",
        "segment": "C",
        "powertrain": "N/A",
        "sales": {
            "2000": 0,
            "2001": 0,
            "2002": 0,
            "2003": 0,
            "2004": 0,
            "2005": 0,
            "2006": 0,
            "2007": 0,
            "2008": 0,
            "2009": 0,
            "2010": 245,
            "2011": 0,
            "2012": 2,
            "2013": 0,
            "2014": 0,
            "2015": 0,
            "2016": 0,
            "2017": 0,
            "2018": 0,
            "2019": 0,
            "2020": 0,
            "2021": 0,
            "2022": 0,
            "2023": 0
        }
    },
    {
        "country": "COL",
        "make": "VW",
        "model": "Bora",
        "type": "Cars",
        "segment": "C",
        "powertrain": "N/A",
        "sales": {
            "2000": 0,
            "2001": 0,
            "2002": 0,
            "2003": 0,
            "2004": 0,
            "2005": 0,
            "2006": 0,
            "2007": 0,
            "2008": 0,
            "2009": 0,
            "2010": 606,
            "2011": 2,
            "2012": 0,
            "2013": 0,
            "2014": 0,
            "2015": 0,
            "2016": 0,
            "2017": 0,
            "2018": 0,
            "2019": 0,
            "2020": 0,
            "2021": 0,
            "2022": 0,
            "2023": 0
        }
    },
    {
        "country": "COL",
        "make": "VW",
        "model": "Golf",
        "type": "Cars",
        "segment": "C",
        "powertrain": "N/A",
        "sales": {
            "2000": 0,
            "2001": 0,
            "2002": 0,
            "2003": 0,
            "2004": 0,
            "2005": 0,
            "2006": 0,
            "2007": 0,
            "2008": 0,
            "2009": 0,
            "2010": 2,
            "2011": 0,
            "2012": 1,
            "2013": 0,
            "2014": 0,
            "2015": 0,
            "2016": 0,
            "2017": 0,
            "2018": 636,
            "2019": 1220,
            "2020": 1111,
            "2021": 2,
            "2022": 0,
            "2023": 0
        }
    },
    {
        "country": "COL",
        "make": "VW",
        "model": "Jetta",
        "type": "Cars",
        "segment": "C",
        "powertrain": "N/A",
        "sales": {
            "2000": 0,
            "2001": 0,
            "2002": 0,
            "2003": 0,
            "2004": 0,
            "2005": 0,
            "2006": 0,
            "2007": 0,
            "2008": 0,
            "2009": 0,
            "2010": 2505,
            "2011": 3524,
            "2012": 3607,
            "2013": 3681,
            "2014": 4226,
            "2015": 4034,
            "2016": 3954,
            "2017": 3120,
            "2018": 1930,
            "2019": 2114,
            "2020": 1205,
            "2021": 107,
            "2022": 325,
            "2023": 0
        }
    },
    {
        "country": "COL",
        "make": "VW",
        "model": "Parati",
        "type": "Cars",
        "segment": "C",
        "powertrain": "N/A",
        "sales": {
            "2000": 0,
            "2001": 0,
            "2002": 0,
            "2003": 0,
            "2004": 0,
            "2005": 0,
            "2006": 0,
            "2007": 0,
            "2008": 0,
            "2009": 0,
            "2010": 2,
            "2011": 0,
            "2012": 0,
            "2013": 0,
            "2014": 0,
            "2015": 0,
            "2016": 0,
            "2017": 0,
            "2018": 0,
            "2019": 0,
            "2020": 0,
            "2021": 0,
            "2022": 0,
            "2023": 0
        }
    },
    {
        "country": "COL",
        "make": "VW",
        "model": "Parati",
        "type": "Cars",
        "segment": "C",
        "powertrain": null,
        "sales": {
            "2000": 0,
            "2001": 0,
            "2002": 0,
            "2003": 0,
            "2004": 0,
            "2005": 0,
            "2006": 0,
            "2007": 0,
            "2008": 0,
            "2009": 0,
            "2010": 3360,
            "2011": 3526,
            "2012": 3610,
            "2013": 3681,
            "2014": 4226,
            "2015": 4034,
            "2016": 3954,
            "2017": 3120,
            "2018": 2566,
            "2019": 3334,
            "2020": 2316,
            "2021": 109,
            "2022": 325,
            "2023": 0
        }
    },
    {
        "country": "COL",
        "make": "VW",
        "model": "Passat (Santana)",
        "type": "Cars",
        "segment": "D",
        "powertrain": "N/A",
        "sales": {
            "2000": 0,
            "2001": 0,
            "2002": 0,
            "2003": 0,
            "2004": 0,
            "2005": 0,
            "2006": 0,
            "2007": 0,
            "2008": 0,
            "2009": 0,
            "2010": 4,
            "2011": 1,
            "2012": 0,
            "2013": 0,
            "2014": 0,
            "2015": 0,
            "2016": 0,
            "2017": 0,
            "2018": 987,
            "2019": 943,
            "2020": 1037,
            "2021": 0,
            "2022": 0,
            "2023": 0
        }
    },
    {
        "country": "COL",
        "make": "VW",
        "model": "Passat CC",
        "type": "Cars",
        "segment": "D",
        "powertrain": "N/A",
        "sales": {
            "2000": 0,
            "2001": 0,
            "2002": 0,
            "2003": 0,
            "2004": 0,
            "2005": 0,
            "2006": 0,
            "2007": 0,
            "2008": 0,
            "2009": 0,
            "2010": 1,
            "2011": 2,
            "2012": 0,
            "2013": 0,
            "2014": 0,
            "2015": 0,
            "2016": 0,
            "2017": 0,
            "2018": 0,
            "2019": 0,
            "2020": 0,
            "2021": 0,
            "2022": 0,
            "2023": 0
        }
    },
    {
        "country": "COL",
        "make": "VW",
        "model": "Passat CC",
        "type": "Cars",
        "segment": "D",
        "powertrain": null,
        "sales": {
            "2000": 0,
            "2001": 0,
            "2002": 0,
            "2003": 0,
            "2004": 0,
            "2005": 0,
            "2006": 0,
            "2007": 0,
            "2008": 0,
            "2009": 0,
            "2010": 5,
            "2011": 3,
            "2012": 0,
            "2013": 0,
            "2014": 0,
            "2015": 0,
            "2016": 0,
            "2017": 0,
            "2018": 987,
            "2019": 943,
            "2020": 1037,
            "2021": 0,
            "2022": 0,
            "2023": 0
        }
    },
    {
        "country": "COL",
        "make": "VW",
        "model": "Nivus",
        "type": "Cars",
        "segment": "SUV-C",
        "powertrain": "N/A",
        "sales": {
            "2000": 0,
            "2001": 0,
            "2002": 0,
            "2003": 0,
            "2004": 0,
            "2005": 0,
            "2006": 0,
            "2007": 0,
            "2008": 0,
            "2009": 0,
            "2010": 0,
            "2011": 0,
            "2012": 0,
            "2013": 0,
            "2014": 0,
            "2015": 0,
            "2016": 0,
            "2017": 0,
            "2018": 0,
            "2019": 0,
            "2020": 0,
            "2021": 1405,
            "2022": 497,
            "2023": 0
        }
    },
    {
        "country": "COL",
        "make": "VW",
        "model": "Tiguan",
        "type": "Cars",
        "segment": "SUV-C",
        "powertrain": "N/A",
        "sales": {
            "2000": 0,
            "2001": 0,
            "2002": 0,
            "2003": 0,
            "2004": 0,
            "2005": 0,
            "2006": 0,
            "2007": 0,
            "2008": 0,
            "2009": 0,
            "2010": 396,
            "2011": 376,
            "2012": 439,
            "2013": 0,
            "2014": 0,
            "2015": 0,
            "2016": 0,
            "2017": 0,
            "2018": 0,
            "2019": 0,
            "2020": 0,
            "2021": 0,
            "2022": 0,
            "2023": 0
        }
    },
    {
        "country": "COL",
        "make": "VW",
        "model": "Tiguan",
        "type": "Cars",
        "segment": "SUV-C",
        "powertrain": null,
        "sales": {
            "2000": 0,
            "2001": 0,
            "2002": 0,
            "2003": 0,
            "2004": 0,
            "2005": 0,
            "2006": 0,
            "2007": 0,
            "2008": 0,
            "2009": 0,
            "2010": 396,
            "2011": 376,
            "2012": 439,
            "2013": 0,
            "2014": 0,
            "2015": 0,
            "2016": 0,
            "2017": 0,
            "2018": 0,
            "2019": 0,
            "2020": 0,
            "2021": 1405,
            "2022": 497,
            "2023": 0
        }
    },
    {
        "country": "COL",
        "make": "VW",
        "model": "Touareg",
        "type": "Cars",
        "segment": "SUV-E",
        "powertrain": "N/A",
        "sales": {
            "2000": 0,
            "2001": 0,
            "2002": 0,
            "2003": 0,
            "2004": 0,
            "2005": 0,
            "2006": 0,
            "2007": 0,
            "2008": 0,
            "2009": 0,
            "2010": 18,
            "2011": 0,
            "2012": 24,
            "2013": 0,
            "2014": 0,
            "2015": 0,
            "2016": 0,
            "2017": 0,
            "2018": 0,
            "2019": 0,
            "2020": 0,
            "2021": 0,
            "2022": 0,
            "2023": 0
        }
    },
    {
        "country": "COL",
        "make": "VW",
        "model": "Touareg",
        "type": "Cars",
        "segment": "SUV-E",
        "powertrain": null,
        "sales": {
            "2000": 0,
            "2001": 0,
            "2002": 0,
            "2003": 0,
            "2004": 0,
            "2005": 0,
            "2006": 0,
            "2007": 0,
            "2008": 0,
            "2009": 0,
            "2010": 18,
            "2011": 0,
            "2012": 24,
            "2013": 0,
            "2014": 0,
            "2015": 0,
            "2016": 0,
            "2017": 0,
            "2018": 0,
            "2019": 0,
            "2020": 0,
            "2021": 0,
            "2022": 0,
            "2023": 0
        }
    },
    {
        "country": "COL",
        "make": "VW",
        "model": "Amarok",
        "type": "Cars",
        "segment": "Pickup Truck",
        "powertrain": "N/A",
        "sales": {
            "2000": 0,
            "2001": 0,
            "2002": 0,
            "2003": 0,
            "2004": 0,
            "2005": 0,
            "2006": 0,
            "2007": 0,
            "2008": 0,
            "2009": 0,
            "2010": 725,
            "2011": 1184,
            "2012": 1300,
            "2013": 0,
            "2014": 0,
            "2015": 0,
            "2016": 0,
            "2017": 0,
            "2018": 0,
            "2019": 0,
            "2020": 0,
            "2021": 0,
            "2022": 0,
            "2023": 0
        }
    },
    {
        "country": "COL",
        "make": "VW",
        "model": "Saveiro",
        "type": "Cars",
        "segment": "Pickup Truck",
        "powertrain": "N/A",
        "sales": {
            "2000": 0,
            "2001": 0,
            "2002": 0,
            "2003": 0,
            "2004": 0,
            "2005": 0,
            "2006": 0,
            "2007": 0,
            "2008": 0,
            "2009": 0,
            "2010": 0,
            "2011": 0,
            "2012": 69,
            "2013": 0,
            "2014": 0,
            "2015": 0,
            "2016": 0,
            "2017": 0,
            "2018": 0,
            "2019": 0,
            "2020": 0,
            "2021": 0,
            "2022": 0,
            "2023": 0
        }
    },
    {
        "country": "COL",
        "make": "VW",
        "model": "Saveiro",
        "type": "Cars",
        "segment": "Pickup Truck",
        "powertrain": null,
        "sales": {
            "2000": 0,
            "2001": 0,
            "2002": 0,
            "2003": 0,
            "2004": 0,
            "2005": 0,
            "2006": 0,
            "2007": 0,
            "2008": 0,
            "2009": 0,
            "2010": 725,
            "2011": 1184,
            "2012": 1369,
            "2013": 0,
            "2014": 0,
            "2015": 0,
            "2016": 0,
            "2017": 0,
            "2018": 0,
            "2019": 0,
            "2020": 0,
            "2021": 0,
            "2022": 0,
            "2023": 0
        }
    },
    {
        "country": "COL",
        "make": "VW",
        "model": "Saveiro",
        "type": "Cars",
        "segment": "Pickup Truck",
        "powertrain": null,
        "sales": {
            "2000": 0,
            "2001": 0,
            "2002": 0,
            "2003": 0,
            "2004": 0,
            "2005": 0,
            "2006": 0,
            "2007": 0,
            "2008": 0,
            "2009": 0,
            "2010": 6173,
            "2011": 6891,
            "2012": 9247,
            "2013": 7032,
            "2014": 7524,
            "2015": 6696,
            "2016": 7312,
            "2017": 6509,
            "2018": 8989,
            "2019": 10394,
            "2020": 6550,
            "2021": 9143,
            "2022": 9196,
            "2023": 0
        }
    },
    {
        "country": "COL",
        "make": "VW",
        "model": "T-Cross",
        "type": "SUV",
        "segment": "SUV-C",
        "powertrain": "N/A",
        "sales": {
            "2000": 0,
            "2001": 0,
            "2002": 0,
            "2003": 0,
            "2004": 0,
            "2005": 0,
            "2006": 0,
            "2007": 0,
            "2008": 0,
            "2009": 0,
            "2010": 0,
            "2011": 0,
            "2012": 0,
            "2013": 0,
            "2014": 0,
            "2015": 0,
            "2016": 0,
            "2017": 0,
            "2018": 0,
            "2019": 0,
            "2020": 0,
            "2021": 2064,
            "2022": 1944,
            "2023": 0
        }
    },
    {
        "country": "COL",
        "make": "VW",
        "model": "Taos",
        "type": "SUV",
        "segment": "SUV-C",
        "powertrain": "N/A",
        "sales": {
            "2000": 0,
            "2001": 0,
            "2002": 0,
            "2003": 0,
            "2004": 0,
            "2005": 0,
            "2006": 0,
            "2007": 0,
            "2008": 0,
            "2009": 0,
            "2010": 0,
            "2011": 0,
            "2012": 0,
            "2013": 0,
            "2014": 0,
            "2015": 0,
            "2016": 0,
            "2017": 0,
            "2018": 0,
            "2019": 0,
            "2020": 0,
            "2021": 646,
            "2022": 1360,
            "2023": 0
        }
    },
    {
        "country": "COL",
        "make": "VW",
        "model": "Tiguan",
        "type": "SUV",
        "segment": "SUV-C",
        "powertrain": "N/A",
        "sales": {
            "2000": 0,
            "2001": 0,
            "2002": 0,
            "2003": 0,
            "2004": 0,
            "2005": 0,
            "2006": 0,
            "2007": 0,
            "2008": 0,
            "2009": 0,
            "2010": 0,
            "2011": 0,
            "2012": 0,
            "2013": 258,
            "2014": 262,
            "2015": 243,
            "2016": 217,
            "2017": 218,
            "2018": 368,
            "2019": 745,
            "2020": 1137,
            "2021": 139,
            "2022": 363,
            "2023": 0
        }
    },
    {
        "country": "COL",
        "make": "VW",
        "model": "Tiguan",
        "type": "SUV",
        "segment": "SUV-C",
        "powertrain": null,
        "sales": {
            "2000": 0,
            "2001": 0,
            "2002": 0,
            "2003": 0,
            "2004": 0,
            "2005": 0,
            "2006": 0,
            "2007": 0,
            "2008": 0,
            "2009": 0,
            "2010": 0,
            "2011": 0,
            "2012": 0,
            "2013": 258,
            "2014": 262,
            "2015": 243,
            "2016": 217,
            "2017": 218,
            "2018": 368,
            "2019": 745,
            "2020": 1137,
            "2021": 2849,
            "2022": 3667,
            "2023": 0
        }
    },
    {
        "country": "COL",
        "make": "VW",
        "model": "Teramont",
        "type": "SUV",
        "segment": "SUV-D",
        "powertrain": "N/A",
        "sales": {
            "2000": 0,
            "2001": 0,
            "2002": 0,
            "2003": 0,
            "2004": 0,
            "2005": 0,
            "2006": 0,
            "2007": 0,
            "2008": 0,
            "2009": 0,
            "2010": 0,
            "2011": 0,
            "2012": 0,
            "2013": 0,
            "2014": 0,
            "2015": 0,
            "2016": 0,
            "2017": 0,
            "2018": 0,
            "2019": 0,
            "2020": 0,
            "2021": 86,
            "2022": 153,
            "2023": 0
        }
    },
    {
        "country": "COL",
        "make": "VW",
        "model": "VW Atlas",
        "type": "SUV",
        "segment": "SUV-D",
        "powertrain": "N/A",
        "sales": {
            "2000": 0,
            "2001": 0,
            "2002": 0,
            "2003": 0,
            "2004": 0,
            "2005": 0,
            "2006": 0,
            "2007": 0,
            "2008": 0,
            "2009": 0,
            "2010": 0,
            "2011": 0,
            "2012": 0,
            "2013": 0,
            "2014": 0,
            "2015": 0,
            "2016": 0,
            "2017": 0,
            "2018": 0,
            "2019": 0,
            "2020": 0,
            "2021": 1,
            "2022": 0,
            "2023": 0
        }
    },
    {
        "country": "COL",
        "make": "VW",
        "model": "VW Atlas",
        "type": "SUV",
        "segment": "SUV-D",
        "powertrain": null,
        "sales": {
            "2000": 0,
            "2001": 0,
            "2002": 0,
            "2003": 0,
            "2004": 0,
            "2005": 0,
            "2006": 0,
            "2007": 0,
            "2008": 0,
            "2009": 0,
            "2010": 0,
            "2011": 0,
            "2012": 0,
            "2013": 0,
            "2014": 0,
            "2015": 0,
            "2016": 0,
            "2017": 0,
            "2018": 0,
            "2019": 0,
            "2020": 0,
            "2021": 87,
            "2022": 153,
            "2023": 0
        }
    },
    {
        "country": "COL",
        "make": "VW",
        "model": "Touareg",
        "type": "SUV",
        "segment": "SUV-E",
        "powertrain": "N/A",
        "sales": {
            "2000": 0,
            "2001": 0,
            "2002": 0,
            "2003": 0,
            "2004": 0,
            "2005": 0,
            "2006": 0,
            "2007": 0,
            "2008": 0,
            "2009": 0,
            "2010": 0,
            "2011": 0,
            "2012": 0,
            "2013": 0,
            "2014": 0,
            "2015": 0,
            "2016": 0,
            "2017": 0,
            "2018": 0,
            "2019": 0,
            "2020": 0,
            "2021": 5,
            "2022": 0,
            "2023": 0
        }
    },
    {
        "country": "COL",
        "make": "VW",
        "model": "Touareg",
        "type": "SUV",
        "segment": "SUV-E",
        "powertrain": null,
        "sales": {
            "2000": 0,
            "2001": 0,
            "2002": 0,
            "2003": 0,
            "2004": 0,
            "2005": 0,
            "2006": 0,
            "2007": 0,
            "2008": 0,
            "2009": 0,
            "2010": 0,
            "2011": 0,
            "2012": 0,
            "2013": 0,
            "2014": 0,
            "2015": 0,
            "2016": 0,
            "2017": 0,
            "2018": 0,
            "2019": 0,
            "2020": 0,
            "2021": 5,
            "2022": 0,
            "2023": 0
        }
    },
    {
        "country": "COL",
        "make": "VW",
        "model": "Touareg",
        "type": "SUV",
        "segment": "SUV-E",
        "powertrain": null,
        "sales": {
            "2000": 0,
            "2001": 0,
            "2002": 0,
            "2003": 0,
            "2004": 0,
            "2005": 0,
            "2006": 0,
            "2007": 0,
            "2008": 0,
            "2009": 0,
            "2010": 0,
            "2011": 0,
            "2012": 0,
            "2013": 258,
            "2014": 262,
            "2015": 243,
            "2016": 217,
            "2017": 218,
            "2018": 368,
            "2019": 745,
            "2020": 1137,
            "2021": 2941,
            "2022": 3820,
            "2023": 0
        }
    },
    {
        "country": "COL",
        "make": "VW",
        "model": "Amarok",
        "type": "Pickup",
        "segment": "Pickup Truck",
        "powertrain": "N/A",
        "sales": {
            "2000": 0,
            "2001": 0,
            "2002": 0,
            "2003": 0,
            "2004": 0,
            "2005": 0,
            "2006": 0,
            "2007": 0,
            "2008": 0,
            "2009": 0,
            "2010": 0,
            "2011": 0,
            "2012": 0,
            "2013": 1380,
            "2014": 1406,
            "2015": 1162,
            "2016": 1018,
            "2017": 1486,
            "2018": 2116,
            "2019": 2067,
            "2020": 1151,
            "2021": 865,
            "2022": 911,
            "2023": 0
        }
    },
    {
        "country": "COL",
        "make": "VW",
        "model": "Saveiro",
        "type": "Pickup",
        "segment": "Pickup Truck",
        "powertrain": "N/A",
        "sales": {
            "2000": 0,
            "2001": 0,
            "2002": 0,
            "2003": 0,
            "2004": 0,
            "2005": 0,
            "2006": 0,
            "2007": 0,
            "2008": 0,
            "2009": 0,
            "2010": 0,
            "2011": 0,
            "2012": 0,
            "2013": 73,
            "2014": 0,
            "2015": 0,
            "2016": 0,
            "2017": 0,
            "2018": 0,
            "2019": 0,
            "2020": 0,
            "2021": 0,
            "2022": 0,
            "2023": 0
        }
    },
    {
        "country": "COL",
        "make": "VW",
        "model": "Saveiro",
        "type": "Pickup",
        "segment": "Pickup Truck",
        "powertrain": null,
        "sales": {
            "2000": 0,
            "2001": 0,
            "2002": 0,
            "2003": 0,
            "2004": 0,
            "2005": 0,
            "2006": 0,
            "2007": 0,
            "2008": 0,
            "2009": 0,
            "2010": 0,
            "2011": 0,
            "2012": 0,
            "2013": 1453,
            "2014": 1406,
            "2015": 1162,
            "2016": 1018,
            "2017": 1486,
            "2018": 2116,
            "2019": 2067,
            "2020": 1151,
            "2021": 865,
            "2022": 911,
            "2023": 0
        }
    },
    {
        "country": "COL",
        "make": "VW",
        "model": "N/A",
        "type": "Pickup",
        "segment": "Unclassified",
        "powertrain": "N/A",
        "sales": {
            "2000": 0,
            "2001": 0,
            "2002": 0,
            "2003": 0,
            "2004": 0,
            "2005": 0,
            "2006": 0,
            "2007": 0,
            "2008": 0,
            "2009": 0,
            "2010": 0,
            "2011": 0,
            "2012": 0,
            "2013": 0,
            "2014": 0,
            "2015": 0,
            "2016": 0,
            "2017": 0,
            "2018": 0,
            "2019": 0,
            "2020": 0,
            "2021": 14,
            "2022": 10,
            "2023": 0
        }
    },
    {
        "country": "COL",
        "make": "VW",
        "model": "N/A",
        "type": "Pickup",
        "segment": "Unclassified",
        "powertrain": null,
        "sales": {
            "2000": 0,
            "2001": 0,
            "2002": 0,
            "2003": 0,
            "2004": 0,
            "2005": 0,
            "2006": 0,
            "2007": 0,
            "2008": 0,
            "2009": 0,
            "2010": 0,
            "2011": 0,
            "2012": 0,
            "2013": 0,
            "2014": 0,
            "2015": 0,
            "2016": 0,
            "2017": 0,
            "2018": 0,
            "2019": 0,
            "2020": 0,
            "2021": 14,
            "2022": 10,
            "2023": 0
        }
    },
    {
        "country": "COL",
        "make": "VW",
        "model": "N/A",
        "type": "Pickup",
        "segment": "Unclassified",
        "powertrain": null,
        "sales": {
            "2000": 0,
            "2001": 0,
            "2002": 0,
            "2003": 0,
            "2004": 0,
            "2005": 0,
            "2006": 0,
            "2007": 0,
            "2008": 0,
            "2009": 0,
            "2010": 0,
            "2011": 0,
            "2012": 0,
            "2013": 1453,
            "2014": 1406,
            "2015": 1162,
            "2016": 1018,
            "2017": 1486,
            "2018": 2116,
            "2019": 2067,
            "2020": 1151,
            "2021": 879,
            "2022": 921,
            "2023": 0
        }
    },
    {
        "country": "COL",
        "make": "VW",
        "model": "Saveiro",
        "type": "CV",
        "segment": "Pickup Truck",
        "powertrain": "N/A",
        "sales": {
            "2000": 0,
            "2001": 0,
            "2002": 0,
            "2003": 0,
            "2004": 0,
            "2005": 0,
            "2006": 0,
            "2007": 0,
            "2008": 0,
            "2009": 0,
            "2010": 0,
            "2011": 0,
            "2012": 0,
            "2013": 0,
            "2014": 0,
            "2015": 0,
            "2016": 0,
            "2017": 0,
            "2018": 0,
            "2019": 0,
            "2020": 0,
            "2021": 198,
            "2022": 269,
            "2023": 0
        }
    },
    {
        "country": "COL",
        "make": "VW",
        "model": "Saveiro",
        "type": "CV",
        "segment": "Pickup Truck",
        "powertrain": null,
        "sales": {
            "2000": 0,
            "2001": 0,
            "2002": 0,
            "2003": 0,
            "2004": 0,
            "2005": 0,
            "2006": 0,
            "2007": 0,
            "2008": 0,
            "2009": 0,
            "2010": 0,
            "2011": 0,
            "2012": 0,
            "2013": 0,
            "2014": 0,
            "2015": 0,
            "2016": 0,
            "2017": 0,
            "2018": 0,
            "2019": 0,
            "2020": 0,
            "2021": 198,
            "2022": 269,
            "2023": 0
        }
    },
    {
        "country": "COL",
        "make": "VW",
        "model": "Delivery",
        "type": "CV",
        "segment": "Unclassified",
        "powertrain": "N/A",
        "sales": {
            "2000": 0,
            "2001": 0,
            "2002": 0,
            "2003": 0,
            "2004": 0,
            "2005": 0,
            "2006": 0,
            "2007": 0,
            "2008": 0,
            "2009": 0,
            "2010": 0,
            "2011": 0,
            "2012": 0,
            "2013": 0,
            "2014": 0,
            "2015": 0,
            "2016": 0,
            "2017": 0,
            "2018": 0,
            "2019": 0,
            "2020": 0,
            "2021": 101,
            "2022": 133,
            "2023": 0
        }
    },
    {
        "country": "COL",
        "make": "VW",
        "model": "N/A",
        "type": "CV",
        "segment": "Unclassified",
        "powertrain": "N/A",
        "sales": {
            "2000": 0,
            "2001": 0,
            "2002": 0,
            "2003": 0,
            "2004": 0,
            "2005": 0,
            "2006": 0,
            "2007": 0,
            "2008": 0,
            "2009": 0,
            "2010": 0,
            "2011": 0,
            "2012": 0,
            "2013": 0,
            "2014": 0,
            "2015": 0,
            "2016": 0,
            "2017": 0,
            "2018": 0,
            "2019": 0,
            "2020": 0,
            "2021": 551,
            "2022": 820,
            "2023": 0
        }
    },
    {
        "country": "COL",
        "make": "VW",
        "model": "N/A",
        "type": "CV",
        "segment": "Unclassified",
        "powertrain": null,
        "sales": {
            "2000": 0,
            "2001": 0,
            "2002": 0,
            "2003": 0,
            "2004": 0,
            "2005": 0,
            "2006": 0,
            "2007": 0,
            "2008": 0,
            "2009": 0,
            "2010": 0,
            "2011": 0,
            "2012": 0,
            "2013": 0,
            "2014": 0,
            "2015": 0,
            "2016": 0,
            "2017": 0,
            "2018": 0,
            "2019": 0,
            "2020": 0,
            "2021": 652,
            "2022": 953,
            "2023": 0
        }
    },
    {
        "country": "COL",
        "make": "VW",
        "model": "N/A",
        "type": "CV",
        "segment": "Unclassified",
        "powertrain": null,
        "sales": {
            "2000": 0,
            "2001": 0,
            "2002": 0,
            "2003": 0,
            "2004": 0,
            "2005": 0,
            "2006": 0,
            "2007": 0,
            "2008": 0,
            "2009": 0,
            "2010": 0,
            "2011": 0,
            "2012": 0,
            "2013": 0,
            "2014": 0,
            "2015": 0,
            "2016": 0,
            "2017": 0,
            "2018": 0,
            "2019": 0,
            "2020": 0,
            "2021": 850,
            "2022": 1222,
            "2023": 0
        }
    },
    {
        "country": "COL",
        "make": "VW",
        "model": "Caddy",
        "type": "Light Trucks",
        "segment": "Unclassified",
        "powertrain": "N/A",
        "sales": {
            "2000": 0,
            "2001": 0,
            "2002": 0,
            "2003": 0,
            "2004": 0,
            "2005": 0,
            "2006": 0,
            "2007": 0,
            "2008": 0,
            "2009": 0,
            "2010": 10,
            "2011": 0,
            "2012": 0,
            "2013": 0,
            "2014": 0,
            "2015": 0,
            "2016": 0,
            "2017": 0,
            "2018": 0,
            "2019": 0,
            "2020": 0,
            "2021": 0,
            "2022": 0,
            "2023": 0
        }
    },
    {
        "country": "COL",
        "make": "VW",
        "model": "Crafter",
        "type": "Light Trucks",
        "segment": "Unclassified",
        "powertrain": "N/A",
        "sales": {
            "2000": 0,
            "2001": 0,
            "2002": 0,
            "2003": 0,
            "2004": 0,
            "2005": 0,
            "2006": 0,
            "2007": 0,
            "2008": 0,
            "2009": 0,
            "2010": 7,
            "2011": 2,
            "2012": 12,
            "2013": 0,
            "2014": 0,
            "2015": 0,
            "2016": 0,
            "2017": 0,
            "2018": 0,
            "2019": 0,
            "2020": 0,
            "2021": 0,
            "2022": 0,
            "2023": 0
        }
    },
    {
        "country": "COL",
        "make": "VW",
        "model": "T5",
        "type": "Light Trucks",
        "segment": "Unclassified",
        "powertrain": "N/A",
        "sales": {
            "2000": 0,
            "2001": 0,
            "2002": 0,
            "2003": 0,
            "2004": 0,
            "2005": 0,
            "2006": 0,
            "2007": 0,
            "2008": 0,
            "2009": 0,
            "2010": 0,
            "2011": 0,
            "2012": 217,
            "2013": 0,
            "2014": 0,
            "2015": 0,
            "2016": 0,
            "2017": 0,
            "2018": 0,
            "2019": 0,
            "2020": 0,
            "2021": 0,
            "2022": 0,
            "2023": 0
        }
    },
    {
        "country": "COL",
        "make": "VW",
        "model": "VW Transporter",
        "type": "Light Trucks",
        "segment": "Unclassified",
        "powertrain": "N/A",
        "sales": {
            "2000": 0,
            "2001": 0,
            "2002": 0,
            "2003": 0,
            "2004": 0,
            "2005": 0,
            "2006": 0,
            "2007": 0,
            "2008": 0,
            "2009": 0,
            "2010": 424,
            "2011": 311,
            "2012": 85,
            "2013": 0,
            "2014": 0,
            "2015": 0,
            "2016": 0,
            "2017": 0,
            "2018": 0,
            "2019": 0,
            "2020": 0,
            "2021": 0,
            "2022": 0,
            "2023": 0
        }
    },
    {
        "country": "COL",
        "make": "VW",
        "model": "VW Transporter",
        "type": "Light Trucks",
        "segment": "Unclassified",
        "powertrain": null,
        "sales": {
            "2000": 0,
            "2001": 0,
            "2002": 0,
            "2003": 0,
            "2004": 0,
            "2005": 0,
            "2006": 0,
            "2007": 0,
            "2008": 0,
            "2009": 0,
            "2010": 441,
            "2011": 313,
            "2012": 314,
            "2013": 0,
            "2014": 0,
            "2015": 0,
            "2016": 0,
            "2017": 0,
            "2018": 0,
            "2019": 0,
            "2020": 0,
            "2021": 0,
            "2022": 0,
            "2023": 0
        }
    },
    {
        "country": "COL",
        "make": "VW",
        "model": "VW Transporter",
        "type": "Light Trucks",
        "segment": "Unclassified",
        "powertrain": null,
        "sales": {
            "2000": 0,
            "2001": 0,
            "2002": 0,
            "2003": 0,
            "2004": 0,
            "2005": 0,
            "2006": 0,
            "2007": 0,
            "2008": 0,
            "2009": 0,
            "2010": 441,
            "2011": 313,
            "2012": 314,
            "2013": 0,
            "2014": 0,
            "2015": 0,
            "2016": 0,
            "2017": 0,
            "2018": 0,
            "2019": 0,
            "2020": 0,
            "2021": 0,
            "2022": 0,
            "2023": 0
        }
    },
    {
        "country": "COL",
        "make": "VW",
        "model": "Crafter",
        "type": "Van",
        "segment": "Unclassified",
        "powertrain": "N/A",
        "sales": {
            "2000": 0,
            "2001": 0,
            "2002": 0,
            "2003": 0,
            "2004": 0,
            "2005": 0,
            "2006": 0,
            "2007": 0,
            "2008": 0,
            "2009": 0,
            "2010": 0,
            "2011": 0,
            "2012": 0,
            "2013": 173,
            "2014": 162,
            "2015": 175,
            "2016": 191,
            "2017": 375,
            "2018": 708,
            "2019": 559,
            "2020": 329,
            "2021": 38,
            "2022": 0,
            "2023": 0
        }
    },
    {
        "country": "COL",
        "make": "VW",
        "model": "VW Transporter",
        "type": "Van",
        "segment": "Unclassified",
        "powertrain": "N/A",
        "sales": {
            "2000": 0,
            "2001": 0,
            "2002": 0,
            "2003": 0,
            "2004": 0,
            "2005": 0,
            "2006": 0,
            "2007": 0,
            "2008": 0,
            "2009": 0,
            "2010": 0,
            "2011": 0,
            "2012": 0,
            "2013": 351,
            "2014": 438,
            "2015": 438,
            "2016": 382,
            "2017": 574,
            "2018": 1191,
            "2019": 350,
            "2020": 433,
            "2021": 0,
            "2022": 0,
            "2023": 0
        }
    },
    {
        "country": "COL",
        "make": "VW",
        "model": "N/A",
        "type": "Van",
        "segment": "Unclassified",
        "powertrain": "N/A",
        "sales": {
            "2000": 0,
            "2001": 0,
            "2002": 0,
            "2003": 0,
            "2004": 0,
            "2005": 0,
            "2006": 0,
            "2007": 0,
            "2008": 0,
            "2009": 0,
            "2010": 0,
            "2011": 0,
            "2012": 0,
            "2013": 0,
            "2014": 0,
            "2015": 0,
            "2016": 0,
            "2017": 0,
            "2018": 0,
            "2019": 0,
            "2020": 0,
            "2021": 168,
            "2022": 0,
            "2023": 0
        }
    },
    {
        "country": "COL",
        "make": "VW",
        "model": "N/A",
        "type": "Van",
        "segment": "Unclassified",
        "powertrain": null,
        "sales": {
            "2000": 0,
            "2001": 0,
            "2002": 0,
            "2003": 0,
            "2004": 0,
            "2005": 0,
            "2006": 0,
            "2007": 0,
            "2008": 0,
            "2009": 0,
            "2010": 0,
            "2011": 0,
            "2012": 0,
            "2013": 524,
            "2014": 600,
            "2015": 613,
            "2016": 573,
            "2017": 949,
            "2018": 1899,
            "2019": 909,
            "2020": 762,
            "2021": 206,
            "2022": 0,
            "2023": 0
        }
    },
    {
        "country": "COL",
        "make": "VW",
        "model": "N/A",
        "type": "Van",
        "segment": "Unclassified",
        "powertrain": null,
        "sales": {
            "2000": 0,
            "2001": 0,
            "2002": 0,
            "2003": 0,
            "2004": 0,
            "2005": 0,
            "2006": 0,
            "2007": 0,
            "2008": 0,
            "2009": 0,
            "2010": 0,
            "2011": 0,
            "2012": 0,
            "2013": 524,
            "2014": 600,
            "2015": 613,
            "2016": 573,
            "2017": 949,
            "2018": 1899,
            "2019": 909,
            "2020": 762,
            "2021": 206,
            "2022": 0,
            "2023": 0
        }
    },
    {
        "country": "COL",
        "make": "VW",
        "model": "N/A",
        "type": "Van",
        "segment": "Unclassified",
        "powertrain": null,
        "sales": {
            "2000": 0,
            "2001": 0,
            "2002": 0,
            "2003": 0,
            "2004": 0,
            "2005": 0,
            "2006": 0,
            "2007": 0,
            "2008": 0,
            "2009": 0,
            "2010": 6614,
            "2011": 7204,
            "2012": 9561,
            "2013": 9267,
            "2014": 9792,
            "2015": 8714,
            "2016": 9120,
            "2017": 9162,
            "2018": 13372,
            "2019": 14115,
            "2020": 9600,
            "2021": 14019,
            "2022": 15159,
            "2023": 0
        }
    },
    {
        "country": "COL",
        "make": "VW",
        "model": "N/A",
        "type": "Van",
        "segment": "Unclassified",
        "powertrain": null,
        "sales": {
            "2000": 0,
            "2001": 0,
            "2002": 0,
            "2003": 0,
            "2004": 0,
            "2005": 0,
            "2006": 0,
            "2007": 0,
            "2008": 0,
            "2009": 0,
            "2010": 6614,
            "2011": 7204,
            "2012": 9561,
            "2013": 9267,
            "2014": 9792,
            "2015": 8714,
            "2016": 9120,
            "2017": 9162,
            "2018": 13372,
            "2019": 14115,
            "2020": 9600,
            "2021": 14019,
            "2022": 15159,
            "2023": 0
        }
    },
    {
        "country": "COL",
        "make": "VW",
        "model": "N/A",
        "type": "Van",
        "segment": "Unclassified",
        "powertrain": null,
        "sales": {
            "2000": 0,
            "2001": 0,
            "2002": 0,
            "2003": 0,
            "2004": 0,
            "2005": 0,
            "2006": 0,
            "2007": 0,
            "2008": 0,
            "2009": 0,
            "2010": 6614,
            "2011": 7204,
            "2012": 9561,
            "2013": 9267,
            "2014": 9792,
            "2015": 8714,
            "2016": 9120,
            "2017": 9162,
            "2018": 13372,
            "2019": 14115,
            "2020": 9600,
            "2021": 14019,
            "2022": 15159,
            "2023": 0
        }
    }
]