[
    {
        "country": "CHN",
        "make": "Skoda",
        "model": "Fabia",
        "type": "Sedan/Hatchback",
        "segment": "B",
        "powertrain": "N/A",
        "sales": {
            "2000": 0,
            "2001": 0,
            "2002": 0,
            "2003": 0,
            "2004": 0,
            "2005": 0,
            "2006": 0,
            "2007": 0,
            "2008": 841,
            "2009": 31279,
            "2010": 39278,
            "2011": 48759,
            "2012": 48380,
            "2013": 33554,
            "2014": 19465,
            "2015": 17073,
            "2016": 12272,
            "2017": 13416,
            "2018": 7224,
            "2019": 1512,
            "2020": 0,
            "2021": 0,
            "2022": 0,
            "2023": 0
        }
    },
    {
        "country": "CHN",
        "make": "Skoda",
        "model": "Fabia",
        "type": "Sedan/Hatchback",
        "segment": "B",
        "powertrain": null,
        "sales": {
            "2000": 0,
            "2001": 0,
            "2002": 0,
            "2003": 0,
            "2004": 0,
            "2005": 0,
            "2006": 0,
            "2007": 0,
            "2008": 841,
            "2009": 31279,
            "2010": 39278,
            "2011": 48759,
            "2012": 48380,
            "2013": 33554,
            "2014": 19465,
            "2015": 17073,
            "2016": 12272,
            "2017": 13416,
            "2018": 7224,
            "2019": 1512,
            "2020": 0,
            "2021": 0,
            "2022": 0,
            "2023": 0
        }
    },
    {
        "country": "CHN",
        "make": "Skoda",
        "model": "Octavia",
        "type": "Sedan/Hatchback",
        "segment": "C",
        "powertrain": "ICE",
        "sales": {
            "2000": 0,
            "2001": 0,
            "2002": 0,
            "2003": 0,
            "2004": 0,
            "2005": 0,
            "2006": 0,
            "2007": 0,
            "2008": 0,
            "2009": 0,
            "2010": 0,
            "2011": 0,
            "2012": 0,
            "2013": 0,
            "2014": 0,
            "2015": 0,
            "2016": 0,
            "2017": 0,
            "2018": 0,
            "2019": 0,
            "2020": 0,
            "2021": 13232,
            "2022": 9347,
            "2023": 0
        }
    },
    {
        "country": "CHN",
        "make": "Skoda",
        "model": "Octavia",
        "type": "Sedan/Hatchback",
        "segment": "C",
        "powertrain": "N/A",
        "sales": {
            "2000": 0,
            "2001": 0,
            "2002": 0,
            "2003": 0,
            "2004": 0,
            "2005": 0,
            "2006": 0,
            "2007": 0,
            "2008": 59499,
            "2009": 82672,
            "2010": 113226,
            "2011": 126450,
            "2012": 137616,
            "2013": 120246,
            "2014": 120509,
            "2015": 150028,
            "2016": 155098,
            "2017": 130193,
            "2018": 105673,
            "2019": 66806,
            "2020": 26737,
            "2021": 0,
            "2022": 0,
            "2023": 0
        }
    },
    {
        "country": "CHN",
        "make": "Skoda",
        "model": "Rapid/Rapid Spaceback",
        "type": "Sedan/Hatchback",
        "segment": "C",
        "powertrain": "ICE",
        "sales": {
            "2000": 0,
            "2001": 0,
            "2002": 0,
            "2003": 0,
            "2004": 0,
            "2005": 0,
            "2006": 0,
            "2007": 0,
            "2008": 0,
            "2009": 0,
            "2010": 0,
            "2011": 0,
            "2012": 0,
            "2013": 0,
            "2014": 0,
            "2015": 0,
            "2016": 0,
            "2017": 0,
            "2018": 0,
            "2019": 0,
            "2020": 0,
            "2021": 10411,
            "2022": 6693,
            "2023": 0
        }
    },
    {
        "country": "CHN",
        "make": "Skoda",
        "model": "Rapid/Rapid Spaceback",
        "type": "Sedan/Hatchback",
        "segment": "C",
        "powertrain": "N/A",
        "sales": {
            "2000": 0,
            "2001": 0,
            "2002": 0,
            "2003": 0,
            "2004": 0,
            "2005": 0,
            "2006": 0,
            "2007": 0,
            "2008": 0,
            "2009": 0,
            "2010": 0,
            "2011": 0,
            "2012": 0,
            "2013": 36052,
            "2014": 96478,
            "2015": 70932,
            "2016": 94676,
            "2017": 88596,
            "2018": 69317,
            "2019": 55570,
            "2020": 35125,
            "2021": 0,
            "2022": 0,
            "2023": 0
        }
    },
    {
        "country": "CHN",
        "make": "Skoda",
        "model": "Rapid/Rapid Spaceback",
        "type": "Sedan/Hatchback",
        "segment": "C",
        "powertrain": null,
        "sales": {
            "2000": 0,
            "2001": 0,
            "2002": 0,
            "2003": 0,
            "2004": 0,
            "2005": 0,
            "2006": 0,
            "2007": 0,
            "2008": 59499,
            "2009": 82672,
            "2010": 113226,
            "2011": 126450,
            "2012": 137616,
            "2013": 156298,
            "2014": 216987,
            "2015": 220960,
            "2016": 249774,
            "2017": 218789,
            "2018": 174990,
            "2019": 122376,
            "2020": 61862,
            "2021": 23643,
            "2022": 16040,
            "2023": 0
        }
    },
    {
        "country": "CHN",
        "make": "Skoda",
        "model": "Skoda Superb/New Superb",
        "type": "Sedan/Hatchback",
        "segment": "D",
        "powertrain": "ICE",
        "sales": {
            "2000": 0,
            "2001": 0,
            "2002": 0,
            "2003": 0,
            "2004": 0,
            "2005": 0,
            "2006": 0,
            "2007": 0,
            "2008": 0,
            "2009": 0,
            "2010": 0,
            "2011": 0,
            "2012": 0,
            "2013": 0,
            "2014": 0,
            "2015": 0,
            "2016": 0,
            "2017": 0,
            "2018": 0,
            "2019": 0,
            "2020": 0,
            "2021": 2129,
            "2022": 2822,
            "2023": 0
        }
    },
    {
        "country": "CHN",
        "make": "Skoda",
        "model": "Skoda Superb/New Superb",
        "type": "Sedan/Hatchback",
        "segment": "D",
        "powertrain": "N/A",
        "sales": {
            "2000": 0,
            "2001": 0,
            "2002": 0,
            "2003": 0,
            "2004": 0,
            "2005": 0,
            "2006": 0,
            "2007": 0,
            "2008": 0,
            "2009": 14624,
            "2010": 37796,
            "2011": 44800,
            "2012": 44007,
            "2013": 37258,
            "2014": 29646,
            "2015": 18448,
            "2016": 41692,
            "2017": 42548,
            "2018": 42234,
            "2019": 23737,
            "2020": 8328,
            "2021": 0,
            "2022": 0,
            "2023": 0
        }
    },
    {
        "country": "CHN",
        "make": "Skoda",
        "model": "Skoda Superb/New Superb",
        "type": "Sedan/Hatchback",
        "segment": "D",
        "powertrain": null,
        "sales": {
            "2000": 0,
            "2001": 0,
            "2002": 0,
            "2003": 0,
            "2004": 0,
            "2005": 0,
            "2006": 0,
            "2007": 0,
            "2008": 0,
            "2009": 14624,
            "2010": 37796,
            "2011": 44800,
            "2012": 44007,
            "2013": 37258,
            "2014": 29646,
            "2015": 18448,
            "2016": 41692,
            "2017": 42548,
            "2018": 42234,
            "2019": 23737,
            "2020": 8328,
            "2021": 2129,
            "2022": 2822,
            "2023": 0
        }
    },
    {
        "country": "CHN",
        "make": "Skoda",
        "model": "Skoda Superb/New Superb",
        "type": "Sedan/Hatchback",
        "segment": "D",
        "powertrain": null,
        "sales": {
            "2000": 0,
            "2001": 0,
            "2002": 0,
            "2003": 0,
            "2004": 0,
            "2005": 0,
            "2006": 0,
            "2007": 0,
            "2008": 60340,
            "2009": 128575,
            "2010": 190300,
            "2011": 220009,
            "2012": 230003,
            "2013": 227110,
            "2014": 266098,
            "2015": 256481,
            "2016": 303738,
            "2017": 274753,
            "2018": 224448,
            "2019": 147625,
            "2020": 70190,
            "2021": 25772,
            "2022": 18862,
            "2023": 0
        }
    },
    {
        "country": "CHN",
        "make": "Skoda",
        "model": "Kamiq",
        "type": "SUV",
        "segment": "SUV-C",
        "powertrain": "ICE",
        "sales": {
            "2000": 0,
            "2001": 0,
            "2002": 0,
            "2003": 0,
            "2004": 0,
            "2005": 0,
            "2006": 0,
            "2007": 0,
            "2008": 0,
            "2009": 0,
            "2010": 0,
            "2011": 0,
            "2012": 0,
            "2013": 0,
            "2014": 0,
            "2015": 0,
            "2016": 0,
            "2017": 0,
            "2018": 0,
            "2019": 0,
            "2020": 0,
            "2021": 18402,
            "2022": 12164,
            "2023": 0
        }
    },
    {
        "country": "CHN",
        "make": "Skoda",
        "model": "Kamiq",
        "type": "SUV",
        "segment": "SUV-C",
        "powertrain": "N/A",
        "sales": {
            "2000": 0,
            "2001": 0,
            "2002": 0,
            "2003": 0,
            "2004": 0,
            "2005": 0,
            "2006": 0,
            "2007": 0,
            "2008": 0,
            "2009": 0,
            "2010": 0,
            "2011": 0,
            "2012": 0,
            "2013": 0,
            "2014": 0,
            "2015": 0,
            "2016": 0,
            "2017": 0,
            "2018": 37143,
            "2019": 52660,
            "2020": 40039,
            "2021": 0,
            "2022": 0,
            "2023": 0
        }
    },
    {
        "country": "CHN",
        "make": "Skoda",
        "model": "Karoq",
        "type": "SUV",
        "segment": "SUV-C",
        "powertrain": "ICE",
        "sales": {
            "2000": 0,
            "2001": 0,
            "2002": 0,
            "2003": 0,
            "2004": 0,
            "2005": 0,
            "2006": 0,
            "2007": 0,
            "2008": 0,
            "2009": 0,
            "2010": 0,
            "2011": 0,
            "2012": 0,
            "2013": 0,
            "2014": 0,
            "2015": 0,
            "2016": 0,
            "2017": 0,
            "2018": 0,
            "2019": 0,
            "2020": 0,
            "2021": 10281,
            "2022": 5205,
            "2023": 0
        }
    },
    {
        "country": "CHN",
        "make": "Skoda",
        "model": "Karoq",
        "type": "SUV",
        "segment": "SUV-C",
        "powertrain": "N/A",
        "sales": {
            "2000": 0,
            "2001": 0,
            "2002": 0,
            "2003": 0,
            "2004": 0,
            "2005": 0,
            "2006": 0,
            "2007": 0,
            "2008": 0,
            "2009": 0,
            "2010": 0,
            "2011": 0,
            "2012": 0,
            "2013": 0,
            "2014": 0,
            "2015": 0,
            "2016": 0,
            "2017": 0,
            "2018": 31071,
            "2019": 38026,
            "2020": 23295,
            "2021": 0,
            "2022": 0,
            "2023": 0
        }
    },
    {
        "country": "CHN",
        "make": "Skoda",
        "model": "Kodiaq",
        "type": "SUV",
        "segment": "SUV-C",
        "powertrain": "ICE",
        "sales": {
            "2000": 0,
            "2001": 0,
            "2002": 0,
            "2003": 0,
            "2004": 0,
            "2005": 0,
            "2006": 0,
            "2007": 0,
            "2008": 0,
            "2009": 0,
            "2010": 0,
            "2011": 0,
            "2012": 0,
            "2013": 0,
            "2014": 0,
            "2015": 0,
            "2016": 0,
            "2017": 0,
            "2018": 0,
            "2019": 0,
            "2020": 0,
            "2021": 1545,
            "2022": 5269,
            "2023": 0
        }
    },
    {
        "country": "CHN",
        "make": "Skoda",
        "model": "Kodiaq",
        "type": "SUV",
        "segment": "SUV-C",
        "powertrain": "N/A",
        "sales": {
            "2000": 0,
            "2001": 0,
            "2002": 0,
            "2003": 0,
            "2004": 0,
            "2005": 0,
            "2006": 0,
            "2007": 0,
            "2008": 0,
            "2009": 0,
            "2010": 0,
            "2011": 0,
            "2012": 0,
            "2013": 0,
            "2014": 0,
            "2015": 0,
            "2016": 0,
            "2017": 44960,
            "2018": 51230,
            "2019": 40067,
            "2020": 17693,
            "2021": 0,
            "2022": 0,
            "2023": 0
        }
    },
    {
        "country": "CHN",
        "make": "Skoda",
        "model": "Yeti",
        "type": "SUV",
        "segment": "SUV-C",
        "powertrain": "N/A",
        "sales": {
            "2000": 0,
            "2001": 0,
            "2002": 0,
            "2003": 0,
            "2004": 0,
            "2005": 0,
            "2006": 0,
            "2007": 0,
            "2008": 0,
            "2009": 0,
            "2010": 0,
            "2011": 0,
            "2012": 0,
            "2013": 4090,
            "2014": 16292,
            "2015": 22981,
            "2016": 26350,
            "2017": 13296,
            "2018": 8108,
            "2019": 0,
            "2020": 0,
            "2021": 0,
            "2022": 0,
            "2023": 0
        }
    },
    {
        "country": "CHN",
        "make": "Skoda",
        "model": "Yeti",
        "type": "SUV",
        "segment": "SUV-C",
        "powertrain": null,
        "sales": {
            "2000": 0,
            "2001": 0,
            "2002": 0,
            "2003": 0,
            "2004": 0,
            "2005": 0,
            "2006": 0,
            "2007": 0,
            "2008": 0,
            "2009": 0,
            "2010": 0,
            "2011": 0,
            "2012": 0,
            "2013": 4090,
            "2014": 16292,
            "2015": 22981,
            "2016": 26350,
            "2017": 58256,
            "2018": 127552,
            "2019": 130753,
            "2020": 81027,
            "2021": 30228,
            "2022": 22638,
            "2023": 0
        }
    },
    {
        "country": "CHN",
        "make": "Skoda",
        "model": "Yeti",
        "type": "SUV",
        "segment": "SUV-C",
        "powertrain": null,
        "sales": {
            "2000": 0,
            "2001": 0,
            "2002": 0,
            "2003": 0,
            "2004": 0,
            "2005": 0,
            "2006": 0,
            "2007": 0,
            "2008": 0,
            "2009": 0,
            "2010": 0,
            "2011": 0,
            "2012": 0,
            "2013": 4090,
            "2014": 16292,
            "2015": 22981,
            "2016": 26350,
            "2017": 58256,
            "2018": 127552,
            "2019": 130753,
            "2020": 81027,
            "2021": 30228,
            "2022": 22638,
            "2023": 0
        }
    },
    {
        "country": "CHN",
        "make": "Skoda",
        "model": "Octavia",
        "type": "Passenger cars",
        "segment": "C",
        "powertrain": "N/A",
        "sales": {
            "2000": 0,
            "2001": 0,
            "2002": 0,
            "2003": 0,
            "2004": 0,
            "2005": 0,
            "2006": 0,
            "2007": 31802,
            "2008": 0,
            "2009": 0,
            "2010": 0,
            "2011": 0,
            "2012": 0,
            "2013": 0,
            "2014": 0,
            "2015": 0,
            "2016": 0,
            "2017": 0,
            "2018": 0,
            "2019": 0,
            "2020": 0,
            "2021": 0,
            "2022": 0,
            "2023": 0
        }
    },
    {
        "country": "CHN",
        "make": "Skoda",
        "model": "Octavia",
        "type": "Passenger cars",
        "segment": "C",
        "powertrain": null,
        "sales": {
            "2000": 0,
            "2001": 0,
            "2002": 0,
            "2003": 0,
            "2004": 0,
            "2005": 0,
            "2006": 0,
            "2007": 31802,
            "2008": 0,
            "2009": 0,
            "2010": 0,
            "2011": 0,
            "2012": 0,
            "2013": 0,
            "2014": 0,
            "2015": 0,
            "2016": 0,
            "2017": 0,
            "2018": 0,
            "2019": 0,
            "2020": 0,
            "2021": 0,
            "2022": 0,
            "2023": 0
        }
    },
    {
        "country": "CHN",
        "make": "Skoda",
        "model": "Octavia",
        "type": "Passenger cars",
        "segment": "C",
        "powertrain": null,
        "sales": {
            "2000": 0,
            "2001": 0,
            "2002": 0,
            "2003": 0,
            "2004": 0,
            "2005": 0,
            "2006": 0,
            "2007": 31802,
            "2008": 0,
            "2009": 0,
            "2010": 0,
            "2011": 0,
            "2012": 0,
            "2013": 0,
            "2014": 0,
            "2015": 0,
            "2016": 0,
            "2017": 0,
            "2018": 0,
            "2019": 0,
            "2020": 0,
            "2021": 0,
            "2022": 0,
            "2023": 0
        }
    },
    {
        "country": "CHN",
        "make": "Skoda",
        "model": "Octavia",
        "type": "Passenger cars",
        "segment": "C",
        "powertrain": null,
        "sales": {
            "2000": 0,
            "2001": 0,
            "2002": 0,
            "2003": 0,
            "2004": 0,
            "2005": 0,
            "2006": 0,
            "2007": 31802,
            "2008": 60340,
            "2009": 128575,
            "2010": 190300,
            "2011": 220009,
            "2012": 230003,
            "2013": 231200,
            "2014": 282390,
            "2015": 279462,
            "2016": 330088,
            "2017": 333009,
            "2018": 352000,
            "2019": 278378,
            "2020": 151217,
            "2021": 56000,
            "2022": 41500,
            "2023": 0
        }
    },
    {
        "country": "CHN",
        "make": "Skoda",
        "model": "Octavia",
        "type": "Passenger cars",
        "segment": "C",
        "powertrain": null,
        "sales": {
            "2000": 0,
            "2001": 0,
            "2002": 0,
            "2003": 0,
            "2004": 0,
            "2005": 0,
            "2006": 0,
            "2007": 31802,
            "2008": 60340,
            "2009": 128575,
            "2010": 190300,
            "2011": 220009,
            "2012": 230003,
            "2013": 231200,
            "2014": 282390,
            "2015": 279462,
            "2016": 330088,
            "2017": 333009,
            "2018": 352000,
            "2019": 278378,
            "2020": 151217,
            "2021": 56000,
            "2022": 41500,
            "2023": 0
        }
    },
    {
        "country": "CHN",
        "make": "Skoda",
        "model": "Octavia",
        "type": "Passenger cars",
        "segment": "C",
        "powertrain": null,
        "sales": {
            "2000": 0,
            "2001": 0,
            "2002": 0,
            "2003": 0,
            "2004": 0,
            "2005": 0,
            "2006": 0,
            "2007": 31802,
            "2008": 60340,
            "2009": 128575,
            "2010": 190300,
            "2011": 220009,
            "2012": 230003,
            "2013": 231200,
            "2014": 282390,
            "2015": 279462,
            "2016": 330088,
            "2017": 333009,
            "2018": 352000,
            "2019": 278378,
            "2020": 151217,
            "2021": 56000,
            "2022": 41500,
            "2023": 0
        }
    }
]