[
    {
        "country": "GRC",
        "make": "Mitsubishi",
        "model": "i-MiEV",
        "type": "Cars",
        "segment": "A",
        "powertrain": "EV",
        "sales": {
            "2000": 0,
            "2001": 0,
            "2002": 0,
            "2003": 0,
            "2004": 0,
            "2005": 0,
            "2006": 0,
            "2007": 0,
            "2008": 0,
            "2009": 0,
            "2010": 0,
            "2011": 0,
            "2012": 1,
            "2013": 0,
            "2014": 0,
            "2015": 0,
            "2016": 0,
            "2017": 0,
            "2018": 0,
            "2019": 0,
            "2020": 0,
            "2021": 0,
            "2022": 0,
            "2023": 0
        }
    },
    {
        "country": "GRC",
        "make": "Mitsubishi",
        "model": "i-MiEV",
        "type": "Cars",
        "segment": "A",
        "powertrain": null,
        "sales": {
            "2000": 0,
            "2001": 0,
            "2002": 0,
            "2003": 0,
            "2004": 0,
            "2005": 0,
            "2006": 0,
            "2007": 0,
            "2008": 0,
            "2009": 0,
            "2010": 0,
            "2011": 0,
            "2012": 1,
            "2013": 0,
            "2014": 0,
            "2015": 0,
            "2016": 0,
            "2017": 0,
            "2018": 0,
            "2019": 0,
            "2020": 0,
            "2021": 0,
            "2022": 0,
            "2023": 0
        }
    },
    {
        "country": "GRC",
        "make": "Mitsubishi",
        "model": "Colt",
        "type": "Cars",
        "segment": "B",
        "powertrain": "N/A",
        "sales": {
            "2000": 0,
            "2001": 0,
            "2002": 0,
            "2003": 0,
            "2004": 0,
            "2005": 0,
            "2006": 0,
            "2007": 3688,
            "2008": 2355,
            "2009": 1572,
            "2010": 687,
            "2011": 289,
            "2012": 115,
            "2013": 54,
            "2014": 7,
            "2015": 0,
            "2016": 0,
            "2017": 0,
            "2018": 0,
            "2019": 0,
            "2020": 0,
            "2021": 0,
            "2022": 0,
            "2023": 0
        }
    },
    {
        "country": "GRC",
        "make": "Mitsubishi",
        "model": "Mirage",
        "type": "Cars",
        "segment": "B",
        "powertrain": "N/A",
        "sales": {
            "2000": 0,
            "2001": 0,
            "2002": 0,
            "2003": 0,
            "2004": 0,
            "2005": 0,
            "2006": 0,
            "2007": 0,
            "2008": 0,
            "2009": 0,
            "2010": 0,
            "2011": 0,
            "2012": 0,
            "2013": 0,
            "2014": 0,
            "2015": 0,
            "2016": 0,
            "2017": 0,
            "2018": 0,
            "2019": 0,
            "2020": 0,
            "2021": 0,
            "2022": 0,
            "2023": 0
        }
    },
    {
        "country": "GRC",
        "make": "Mitsubishi",
        "model": "Space Star",
        "type": "Cars",
        "segment": "B",
        "powertrain": "ICE",
        "sales": {
            "2000": 0,
            "2001": 0,
            "2002": 0,
            "2003": 0,
            "2004": 0,
            "2005": 0,
            "2006": 0,
            "2007": 0,
            "2008": 0,
            "2009": 0,
            "2010": 0,
            "2011": 0,
            "2012": 0,
            "2013": 0,
            "2014": 0,
            "2015": 0,
            "2016": 0,
            "2017": 0,
            "2018": 0,
            "2019": 0,
            "2020": 0,
            "2021": 0,
            "2022": 546,
            "2023": 0
        }
    },
    {
        "country": "GRC",
        "make": "Mitsubishi",
        "model": "Space Star",
        "type": "Cars",
        "segment": "B",
        "powertrain": "N/A",
        "sales": {
            "2000": 0,
            "2001": 0,
            "2002": 0,
            "2003": 0,
            "2004": 0,
            "2005": 0,
            "2006": 0,
            "2007": 5,
            "2008": 0,
            "2009": 0,
            "2010": 0,
            "2011": 0,
            "2012": 0,
            "2013": 7,
            "2014": 90,
            "2015": 116,
            "2016": 50,
            "2017": 155,
            "2018": 152,
            "2019": 225,
            "2020": 195,
            "2021": 206,
            "2022": 0,
            "2023": 0
        }
    },
    {
        "country": "GRC",
        "make": "Mitsubishi",
        "model": "Space Star",
        "type": "Cars",
        "segment": "B",
        "powertrain": null,
        "sales": {
            "2000": 0,
            "2001": 0,
            "2002": 0,
            "2003": 0,
            "2004": 0,
            "2005": 0,
            "2006": 0,
            "2007": 3693,
            "2008": 2355,
            "2009": 1572,
            "2010": 687,
            "2011": 289,
            "2012": 115,
            "2013": 61,
            "2014": 97,
            "2015": 116,
            "2016": 50,
            "2017": 155,
            "2018": 152,
            "2019": 225,
            "2020": 195,
            "2021": 206,
            "2022": 546,
            "2023": 0
        }
    },
    {
        "country": "GRC",
        "make": "Mitsubishi",
        "model": "Lancer",
        "type": "Cars",
        "segment": "C",
        "powertrain": "N/A",
        "sales": {
            "2000": 0,
            "2001": 0,
            "2002": 0,
            "2003": 0,
            "2004": 0,
            "2005": 0,
            "2006": 0,
            "2007": 645,
            "2008": 996,
            "2009": 979,
            "2010": 851,
            "2011": 210,
            "2012": 135,
            "2013": 33,
            "2014": 29,
            "2015": 5,
            "2016": 0,
            "2017": 0,
            "2018": 0,
            "2019": 0,
            "2020": 1,
            "2021": 0,
            "2022": 0,
            "2023": 0
        }
    },
    {
        "country": "GRC",
        "make": "Mitsubishi",
        "model": "Lancer",
        "type": "Cars",
        "segment": "C",
        "powertrain": null,
        "sales": {
            "2000": 0,
            "2001": 0,
            "2002": 0,
            "2003": 0,
            "2004": 0,
            "2005": 0,
            "2006": 0,
            "2007": 645,
            "2008": 996,
            "2009": 979,
            "2010": 851,
            "2011": 210,
            "2012": 135,
            "2013": 33,
            "2014": 29,
            "2015": 5,
            "2016": 0,
            "2017": 0,
            "2018": 0,
            "2019": 0,
            "2020": 1,
            "2021": 0,
            "2022": 0,
            "2023": 0
        }
    },
    {
        "country": "GRC",
        "make": "Mitsubishi",
        "model": "Carisma",
        "type": "Cars",
        "segment": "D",
        "powertrain": "N/A",
        "sales": {
            "2000": 0,
            "2001": 0,
            "2002": 0,
            "2003": 0,
            "2004": 0,
            "2005": 0,
            "2006": 0,
            "2007": 13,
            "2008": 0,
            "2009": 0,
            "2010": 0,
            "2011": 0,
            "2012": 0,
            "2013": 0,
            "2014": 0,
            "2015": 0,
            "2016": 0,
            "2017": 0,
            "2018": 0,
            "2019": 0,
            "2020": 0,
            "2021": 0,
            "2022": 0,
            "2023": 0
        }
    },
    {
        "country": "GRC",
        "make": "Mitsubishi",
        "model": "Carisma",
        "type": "Cars",
        "segment": "D",
        "powertrain": null,
        "sales": {
            "2000": 0,
            "2001": 0,
            "2002": 0,
            "2003": 0,
            "2004": 0,
            "2005": 0,
            "2006": 0,
            "2007": 13,
            "2008": 0,
            "2009": 0,
            "2010": 0,
            "2011": 0,
            "2012": 0,
            "2013": 0,
            "2014": 0,
            "2015": 0,
            "2016": 0,
            "2017": 0,
            "2018": 0,
            "2019": 0,
            "2020": 0,
            "2021": 0,
            "2022": 0,
            "2023": 0
        }
    },
    {
        "country": "GRC",
        "make": "Mitsubishi",
        "model": "Eclipse Cross",
        "type": "Cars",
        "segment": "SUV-C",
        "powertrain": "PHV",
        "sales": {
            "2000": 0,
            "2001": 0,
            "2002": 0,
            "2003": 0,
            "2004": 0,
            "2005": 0,
            "2006": 0,
            "2007": 0,
            "2008": 0,
            "2009": 0,
            "2010": 0,
            "2011": 0,
            "2012": 0,
            "2013": 0,
            "2014": 0,
            "2015": 0,
            "2016": 0,
            "2017": 0,
            "2018": 0,
            "2019": 0,
            "2020": 0,
            "2021": 0,
            "2022": 52,
            "2023": 0
        }
    },
    {
        "country": "GRC",
        "make": "Mitsubishi",
        "model": "Eclipse Cross",
        "type": "Cars",
        "segment": "SUV-C",
        "powertrain": "N/A",
        "sales": {
            "2000": 0,
            "2001": 0,
            "2002": 0,
            "2003": 0,
            "2004": 0,
            "2005": 0,
            "2006": 0,
            "2007": 0,
            "2008": 0,
            "2009": 0,
            "2010": 0,
            "2011": 0,
            "2012": 0,
            "2013": 0,
            "2014": 0,
            "2015": 0,
            "2016": 0,
            "2017": 0,
            "2018": 66,
            "2019": 124,
            "2020": 195,
            "2021": 17,
            "2022": 0,
            "2023": 0
        }
    },
    {
        "country": "GRC",
        "make": "Mitsubishi",
        "model": "RVR (ASX/Outlander Sport)",
        "type": "Cars",
        "segment": "SUV-C",
        "powertrain": "N/A",
        "sales": {
            "2000": 0,
            "2001": 0,
            "2002": 0,
            "2003": 0,
            "2004": 0,
            "2005": 0,
            "2006": 0,
            "2007": 0,
            "2008": 0,
            "2009": 0,
            "2010": 206,
            "2011": 934,
            "2012": 357,
            "2013": 253,
            "2014": 157,
            "2015": 157,
            "2016": 182,
            "2017": 46,
            "2018": 73,
            "2019": 153,
            "2020": 39,
            "2021": 2,
            "2022": 0,
            "2023": 0
        }
    },
    {
        "country": "GRC",
        "make": "Mitsubishi",
        "model": "RVR (ASX/Outlander Sport)",
        "type": "Cars",
        "segment": "SUV-C",
        "powertrain": null,
        "sales": {
            "2000": 0,
            "2001": 0,
            "2002": 0,
            "2003": 0,
            "2004": 0,
            "2005": 0,
            "2006": 0,
            "2007": 0,
            "2008": 0,
            "2009": 0,
            "2010": 206,
            "2011": 934,
            "2012": 357,
            "2013": 253,
            "2014": 157,
            "2015": 157,
            "2016": 182,
            "2017": 46,
            "2018": 139,
            "2019": 277,
            "2020": 234,
            "2021": 19,
            "2022": 52,
            "2023": 0
        }
    },
    {
        "country": "GRC",
        "make": "Mitsubishi",
        "model": "Outlander",
        "type": "Cars",
        "segment": "SUV-D",
        "powertrain": "PHV",
        "sales": {
            "2000": 0,
            "2001": 0,
            "2002": 0,
            "2003": 0,
            "2004": 0,
            "2005": 0,
            "2006": 0,
            "2007": 0,
            "2008": 0,
            "2009": 0,
            "2010": 0,
            "2011": 0,
            "2012": 0,
            "2013": 0,
            "2014": 0,
            "2015": 0,
            "2016": 0,
            "2017": 0,
            "2018": 0,
            "2019": 3,
            "2020": 13,
            "2021": 1,
            "2022": 0,
            "2023": 0
        }
    },
    {
        "country": "GRC",
        "make": "Mitsubishi",
        "model": "Outlander",
        "type": "Cars",
        "segment": "SUV-D",
        "powertrain": "N/A",
        "sales": {
            "2000": 0,
            "2001": 0,
            "2002": 0,
            "2003": 0,
            "2004": 0,
            "2005": 0,
            "2006": 0,
            "2007": 273,
            "2008": 1535,
            "2009": 1064,
            "2010": 107,
            "2011": 6,
            "2012": 0,
            "2013": 1,
            "2014": 0,
            "2015": 1,
            "2016": 1,
            "2017": 0,
            "2018": 0,
            "2019": 0,
            "2020": 0,
            "2021": 0,
            "2022": 0,
            "2023": 0
        }
    },
    {
        "country": "GRC",
        "make": "Mitsubishi",
        "model": "Pajero Sport",
        "type": "Cars",
        "segment": "SUV-D",
        "powertrain": "N/A",
        "sales": {
            "2000": 0,
            "2001": 0,
            "2002": 0,
            "2003": 0,
            "2004": 0,
            "2005": 0,
            "2006": 0,
            "2007": 39,
            "2008": 0,
            "2009": 0,
            "2010": 0,
            "2011": 0,
            "2012": 0,
            "2013": 0,
            "2014": 0,
            "2015": 0,
            "2016": 0,
            "2017": 0,
            "2018": 0,
            "2019": 0,
            "2020": 0,
            "2021": 0,
            "2022": 0,
            "2023": 0
        }
    },
    {
        "country": "GRC",
        "make": "Mitsubishi",
        "model": "Pajero Sport",
        "type": "Cars",
        "segment": "SUV-D",
        "powertrain": null,
        "sales": {
            "2000": 0,
            "2001": 0,
            "2002": 0,
            "2003": 0,
            "2004": 0,
            "2005": 0,
            "2006": 0,
            "2007": 312,
            "2008": 1535,
            "2009": 1064,
            "2010": 107,
            "2011": 6,
            "2012": 0,
            "2013": 1,
            "2014": 0,
            "2015": 1,
            "2016": 1,
            "2017": 0,
            "2018": 0,
            "2019": 3,
            "2020": 13,
            "2021": 1,
            "2022": 0,
            "2023": 0
        }
    },
    {
        "country": "GRC",
        "make": "Mitsubishi",
        "model": "Pajero (Montero)",
        "type": "Cars",
        "segment": "SUV-E",
        "powertrain": "N/A",
        "sales": {
            "2000": 0,
            "2001": 0,
            "2002": 0,
            "2003": 0,
            "2004": 0,
            "2005": 0,
            "2006": 0,
            "2007": 189,
            "2008": 105,
            "2009": 78,
            "2010": 1,
            "2011": 0,
            "2012": 0,
            "2013": 0,
            "2014": 0,
            "2015": 0,
            "2016": 0,
            "2017": 0,
            "2018": 1,
            "2019": 0,
            "2020": 0,
            "2021": 1,
            "2022": 0,
            "2023": 0
        }
    },
    {
        "country": "GRC",
        "make": "Mitsubishi",
        "model": "Pajero (Montero)",
        "type": "Cars",
        "segment": "SUV-E",
        "powertrain": null,
        "sales": {
            "2000": 0,
            "2001": 0,
            "2002": 0,
            "2003": 0,
            "2004": 0,
            "2005": 0,
            "2006": 0,
            "2007": 189,
            "2008": 105,
            "2009": 78,
            "2010": 1,
            "2011": 0,
            "2012": 0,
            "2013": 0,
            "2014": 0,
            "2015": 0,
            "2016": 0,
            "2017": 0,
            "2018": 1,
            "2019": 0,
            "2020": 0,
            "2021": 1,
            "2022": 0,
            "2023": 0
        }
    },
    {
        "country": "GRC",
        "make": "Mitsubishi",
        "model": "Grandis",
        "type": "Cars",
        "segment": "MPV",
        "powertrain": "N/A",
        "sales": {
            "2000": 0,
            "2001": 0,
            "2002": 0,
            "2003": 0,
            "2004": 0,
            "2005": 0,
            "2006": 0,
            "2007": 4,
            "2008": 1,
            "2009": 2,
            "2010": 0,
            "2011": 0,
            "2012": 0,
            "2013": 0,
            "2014": 0,
            "2015": 0,
            "2016": 0,
            "2017": 0,
            "2018": 0,
            "2019": 0,
            "2020": 0,
            "2021": 0,
            "2022": 0,
            "2023": 0
        }
    },
    {
        "country": "GRC",
        "make": "Mitsubishi",
        "model": "Grandis",
        "type": "Cars",
        "segment": "MPV",
        "powertrain": null,
        "sales": {
            "2000": 0,
            "2001": 0,
            "2002": 0,
            "2003": 0,
            "2004": 0,
            "2005": 0,
            "2006": 0,
            "2007": 4,
            "2008": 1,
            "2009": 2,
            "2010": 0,
            "2011": 0,
            "2012": 0,
            "2013": 0,
            "2014": 0,
            "2015": 0,
            "2016": 0,
            "2017": 0,
            "2018": 0,
            "2019": 0,
            "2020": 0,
            "2021": 0,
            "2022": 0,
            "2023": 0
        }
    },
    {
        "country": "GRC",
        "make": "Mitsubishi",
        "model": "N/A",
        "type": "Cars",
        "segment": "Unclassified",
        "powertrain": "N/A",
        "sales": {
            "2000": 0,
            "2001": 0,
            "2002": 0,
            "2003": 0,
            "2004": 0,
            "2005": 0,
            "2006": 0,
            "2007": 16,
            "2008": 3,
            "2009": 1,
            "2010": 0,
            "2011": 0,
            "2012": 0,
            "2013": 0,
            "2014": 0,
            "2015": 0,
            "2016": 0,
            "2017": 0,
            "2018": 0,
            "2019": 0,
            "2020": 0,
            "2021": 0,
            "2022": 0,
            "2023": 0
        }
    },
    {
        "country": "GRC",
        "make": "Mitsubishi",
        "model": "Other/Adjustment",
        "type": "Cars",
        "segment": "Unclassified",
        "powertrain": "N/A",
        "sales": {
            "2000": 0,
            "2001": 0,
            "2002": 0,
            "2003": 0,
            "2004": 0,
            "2005": 0,
            "2006": 0,
            "2007": 0,
            "2008": 0,
            "2009": 0,
            "2010": 1,
            "2011": 1,
            "2012": 0,
            "2013": 0,
            "2014": 0,
            "2015": 0,
            "2016": 0,
            "2017": 0,
            "2018": 0,
            "2019": 0,
            "2020": 0,
            "2021": 0,
            "2022": 0,
            "2023": 0
        }
    },
    {
        "country": "GRC",
        "make": "Mitsubishi",
        "model": "Other/Adjustment",
        "type": "Cars",
        "segment": "Unclassified",
        "powertrain": null,
        "sales": {
            "2000": 0,
            "2001": 0,
            "2002": 0,
            "2003": 0,
            "2004": 0,
            "2005": 0,
            "2006": 0,
            "2007": 16,
            "2008": 3,
            "2009": 1,
            "2010": 1,
            "2011": 1,
            "2012": 0,
            "2013": 0,
            "2014": 0,
            "2015": 0,
            "2016": 0,
            "2017": 0,
            "2018": 0,
            "2019": 0,
            "2020": 0,
            "2021": 0,
            "2022": 0,
            "2023": 0
        }
    },
    {
        "country": "GRC",
        "make": "Mitsubishi",
        "model": "Other/Adjustment",
        "type": "Cars",
        "segment": "Unclassified",
        "powertrain": null,
        "sales": {
            "2000": 0,
            "2001": 0,
            "2002": 0,
            "2003": 0,
            "2004": 0,
            "2005": 0,
            "2006": 0,
            "2007": 4872,
            "2008": 4995,
            "2009": 3696,
            "2010": 1853,
            "2011": 1440,
            "2012": 608,
            "2013": 348,
            "2014": 283,
            "2015": 279,
            "2016": 233,
            "2017": 201,
            "2018": 292,
            "2019": 505,
            "2020": 443,
            "2021": 227,
            "2022": 598,
            "2023": 0
        }
    },
    {
        "country": "GRC",
        "make": "Mitsubishi",
        "model": "Pajero (Montero)",
        "type": "Light Trucks",
        "segment": "SUV-E",
        "powertrain": "N/A",
        "sales": {
            "2000": 0,
            "2001": 0,
            "2002": 0,
            "2003": 0,
            "2004": 0,
            "2005": 0,
            "2006": 0,
            "2007": 7,
            "2008": 2,
            "2009": 0,
            "2010": 0,
            "2011": 0,
            "2012": 0,
            "2013": 0,
            "2014": 0,
            "2015": 0,
            "2016": 0,
            "2017": 0,
            "2018": 0,
            "2019": 0,
            "2020": 0,
            "2021": 0,
            "2022": 0,
            "2023": 0
        }
    },
    {
        "country": "GRC",
        "make": "Mitsubishi",
        "model": "Pajero (Montero)",
        "type": "Light Trucks",
        "segment": "SUV-E",
        "powertrain": null,
        "sales": {
            "2000": 0,
            "2001": 0,
            "2002": 0,
            "2003": 0,
            "2004": 0,
            "2005": 0,
            "2006": 0,
            "2007": 7,
            "2008": 2,
            "2009": 0,
            "2010": 0,
            "2011": 0,
            "2012": 0,
            "2013": 0,
            "2014": 0,
            "2015": 0,
            "2016": 0,
            "2017": 0,
            "2018": 0,
            "2019": 0,
            "2020": 0,
            "2021": 0,
            "2022": 0,
            "2023": 0
        }
    },
    {
        "country": "GRC",
        "make": "Mitsubishi",
        "model": "L200",
        "type": "Light Trucks",
        "segment": "Pickup Truck",
        "powertrain": "N/A",
        "sales": {
            "2000": 0,
            "2001": 0,
            "2002": 0,
            "2003": 0,
            "2004": 0,
            "2005": 0,
            "2006": 0,
            "2007": 1485,
            "2008": 1182,
            "2009": 562,
            "2010": 0,
            "2011": 0,
            "2012": 0,
            "2013": 0,
            "2014": 0,
            "2015": 0,
            "2016": 0,
            "2017": 0,
            "2018": 0,
            "2019": 0,
            "2020": 0,
            "2021": 0,
            "2022": 0,
            "2023": 0
        }
    },
    {
        "country": "GRC",
        "make": "Mitsubishi",
        "model": "L200",
        "type": "Light Trucks",
        "segment": "Pickup Truck",
        "powertrain": null,
        "sales": {
            "2000": 0,
            "2001": 0,
            "2002": 0,
            "2003": 0,
            "2004": 0,
            "2005": 0,
            "2006": 0,
            "2007": 1485,
            "2008": 1182,
            "2009": 562,
            "2010": 0,
            "2011": 0,
            "2012": 0,
            "2013": 0,
            "2014": 0,
            "2015": 0,
            "2016": 0,
            "2017": 0,
            "2018": 0,
            "2019": 0,
            "2020": 0,
            "2021": 0,
            "2022": 0,
            "2023": 0
        }
    },
    {
        "country": "GRC",
        "make": "Mitsubishi",
        "model": "L300",
        "type": "Light Trucks",
        "segment": "Unclassified",
        "powertrain": "N/A",
        "sales": {
            "2000": 0,
            "2001": 0,
            "2002": 0,
            "2003": 0,
            "2004": 0,
            "2005": 0,
            "2006": 0,
            "2007": 1,
            "2008": 0,
            "2009": 1,
            "2010": 0,
            "2011": 0,
            "2012": 0,
            "2013": 0,
            "2014": 0,
            "2015": 0,
            "2016": 0,
            "2017": 0,
            "2018": 0,
            "2019": 0,
            "2020": 0,
            "2021": 0,
            "2022": 0,
            "2023": 0
        }
    },
    {
        "country": "GRC",
        "make": "Mitsubishi",
        "model": "N/A",
        "type": "Light Trucks",
        "segment": "Unclassified",
        "powertrain": "N/A",
        "sales": {
            "2000": 0,
            "2001": 0,
            "2002": 0,
            "2003": 0,
            "2004": 0,
            "2005": 0,
            "2006": 0,
            "2007": 21,
            "2008": 5,
            "2009": 10,
            "2010": 525,
            "2011": 271,
            "2012": 160,
            "2013": 134,
            "2014": 138,
            "2015": 209,
            "2016": 237,
            "2017": 249,
            "2018": 214,
            "2019": 325,
            "2020": 239,
            "2021": 419,
            "2022": 197,
            "2023": 0
        }
    },
    {
        "country": "GRC",
        "make": "Mitsubishi",
        "model": "N/A",
        "type": "Light Trucks",
        "segment": "Unclassified",
        "powertrain": null,
        "sales": {
            "2000": 0,
            "2001": 0,
            "2002": 0,
            "2003": 0,
            "2004": 0,
            "2005": 0,
            "2006": 0,
            "2007": 22,
            "2008": 5,
            "2009": 11,
            "2010": 525,
            "2011": 271,
            "2012": 160,
            "2013": 134,
            "2014": 138,
            "2015": 209,
            "2016": 237,
            "2017": 249,
            "2018": 214,
            "2019": 325,
            "2020": 239,
            "2021": 419,
            "2022": 197,
            "2023": 0
        }
    },
    {
        "country": "GRC",
        "make": "Mitsubishi",
        "model": "N/A",
        "type": "Light Trucks",
        "segment": "Unclassified",
        "powertrain": null,
        "sales": {
            "2000": 0,
            "2001": 0,
            "2002": 0,
            "2003": 0,
            "2004": 0,
            "2005": 0,
            "2006": 0,
            "2007": 1514,
            "2008": 1189,
            "2009": 573,
            "2010": 525,
            "2011": 271,
            "2012": 160,
            "2013": 134,
            "2014": 138,
            "2015": 209,
            "2016": 237,
            "2017": 249,
            "2018": 214,
            "2019": 325,
            "2020": 239,
            "2021": 419,
            "2022": 197,
            "2023": 0
        }
    },
    {
        "country": "GRC",
        "make": "Mitsubishi",
        "model": "N/A",
        "type": "Light Trucks",
        "segment": "Unclassified",
        "powertrain": null,
        "sales": {
            "2000": 0,
            "2001": 0,
            "2002": 0,
            "2003": 0,
            "2004": 0,
            "2005": 0,
            "2006": 0,
            "2007": 6386,
            "2008": 6184,
            "2009": 4269,
            "2010": 2378,
            "2011": 1711,
            "2012": 768,
            "2013": 482,
            "2014": 421,
            "2015": 488,
            "2016": 470,
            "2017": 450,
            "2018": 506,
            "2019": 830,
            "2020": 682,
            "2021": 646,
            "2022": 795,
            "2023": 0
        }
    },
    {
        "country": "GRC",
        "make": "Mitsubishi",
        "model": "N/A",
        "type": "Light Trucks",
        "segment": "Unclassified",
        "powertrain": null,
        "sales": {
            "2000": 0,
            "2001": 0,
            "2002": 0,
            "2003": 0,
            "2004": 0,
            "2005": 0,
            "2006": 0,
            "2007": 6386,
            "2008": 6184,
            "2009": 4269,
            "2010": 2378,
            "2011": 1711,
            "2012": 768,
            "2013": 482,
            "2014": 421,
            "2015": 488,
            "2016": 470,
            "2017": 450,
            "2018": 506,
            "2019": 830,
            "2020": 682,
            "2021": 646,
            "2022": 795,
            "2023": 0
        }
    },
    {
        "country": "GRC",
        "make": "Mitsubishi",
        "model": "N/A",
        "type": "Light Trucks",
        "segment": "Unclassified",
        "powertrain": null,
        "sales": {
            "2000": 0,
            "2001": 0,
            "2002": 0,
            "2003": 0,
            "2004": 0,
            "2005": 0,
            "2006": 0,
            "2007": 6386,
            "2008": 6184,
            "2009": 4269,
            "2010": 2378,
            "2011": 1711,
            "2012": 768,
            "2013": 482,
            "2014": 421,
            "2015": 488,
            "2016": 470,
            "2017": 450,
            "2018": 506,
            "2019": 830,
            "2020": 682,
            "2021": 646,
            "2022": 795,
            "2023": 0
        }
    }
]